Metadata-Version: 2.1
Name: OrdDict
Version: 0.0.1
Summary: This package implement an ordered dict.
Home-page: https://github.com/mauricelambert/OrdDict
Author: Maurice Lambert
Author-email: mauricelambert434@gmail.com
Classifier: Programming Language :: Python
Classifier: Development Status :: 5 - Production/Stable
Classifier: Environment :: Console
Classifier: License :: OSI Approved :: GNU General Public License v3 or later (GPLv3+)
Classifier: Natural Language :: English
Classifier: Operating System :: OS Independent
Classifier: Programming Language :: Python :: 3.8
Requires-Python: >=3.6
